setup.py
probability_dsnd_2020/Binomialdistribution.py
probability_dsnd_2020/Gaussiandistribution.py
probability_dsnd_2020/Generaldistribution.py
probability_dsnd_2020/__init__.py
probability_dsnd_2020.egg-info/PKG-INFO
probability_dsnd_2020.egg-info/SOURCES.txt
probability_dsnd_2020.egg-info/dependency_links.txt
probability_dsnd_2020.egg-info/not-zip-safe
probability_dsnd_2020.egg-info/top_level.txt