Metadata-Version: 1.0
Name: probability-dsnd-2020
Version: 0.1
Summary: Gaussian and Binomial distributions
Home-page: UNKNOWN
Author: awaish kumar
Author-email: awaish.rathi@gmail.com
License: UNKNOWN
Platform: UNKNOWN
